tanu/__init__.py
tanu/__main__.py
tanu/client.py
tanu/config.py
tanu/exceptions.py
tanu/parcel.py
tanu/protocol.py
tanu/rabbitmq.py
tanu/tanu.py
tanu/worker.py
tanu/utils/__init__.py
tanu/utils/object_encoder_decoder.py
tanu-0.5.0.dist-info/METADATA
tanu-0.5.0.dist-info/WHEEL
tanu-0.5.0.dist-info/top_level.txt
tanu-0.5.0.dist-info/RECORD
